cdp/__init__.py
cdp/domains.py
cdp/py.typed
cdp/service.py
cdp/generator/__init__.py
cdp/generator/client_generator.py
cdp/generator/constant.py
cdp/generator/domain_generator.py
cdp/generator/event_generator.py
cdp/generator/method_generator.py
cdp/generator/service.py
cdp/generator/type_generator.py
cdp/protocol/__init__.py
cdp/protocol/py.typed
cdp/protocol/accessibility/__init__.py
cdp/protocol/accessibility/service.py
cdp/protocol/accessibility/types.py
cdp/protocol/accessibility/events/__init__.py
cdp/protocol/accessibility/events/service.py
cdp/protocol/accessibility/events/types.py
cdp/protocol/accessibility/methods/__init__.py
cdp/protocol/accessibility/methods/service.py
cdp/protocol/accessibility/methods/types.py
cdp/protocol/animation/__init__.py
cdp/protocol/animation/service.py
cdp/protocol/animation/types.py
cdp/protocol/animation/events/__init__.py
cdp/protocol/animation/events/service.py
cdp/protocol/animation/events/types.py
cdp/protocol/animation/methods/__init__.py
cdp/protocol/animation/methods/service.py
cdp/protocol/animation/methods/types.py
cdp/protocol/audits/__init__.py
cdp/protocol/audits/service.py
cdp/protocol/audits/types.py
cdp/protocol/audits/events/__init__.py
cdp/protocol/audits/events/service.py
cdp/protocol/audits/events/types.py
cdp/protocol/audits/methods/__init__.py
cdp/protocol/audits/methods/service.py
cdp/protocol/audits/methods/types.py
cdp/protocol/autofill/__init__.py
cdp/protocol/autofill/service.py
cdp/protocol/autofill/types.py
cdp/protocol/autofill/events/__init__.py
cdp/protocol/autofill/events/service.py
cdp/protocol/autofill/events/types.py
cdp/protocol/autofill/methods/__init__.py
cdp/protocol/autofill/methods/service.py
cdp/protocol/autofill/methods/types.py
cdp/protocol/background_service/__init__.py
cdp/protocol/background_service/service.py
cdp/protocol/background_service/types.py
cdp/protocol/background_service/events/__init__.py
cdp/protocol/background_service/events/service.py
chromedeveloperprotocol_client-0.1.1.dist-info/METADATA
chromedeveloperprotocol_client-0.1.1.dist-info/WHEEL
chromedeveloperprotocol_client-0.1.1.dist-info/RECORD
