Metadata-Version: 2.4
Name: chromedeveloperprotocol-client
Version: 0.1.1
Summary: Python wrapper for Chrome DevTools Protocol
Requires-Python: >=3.13
Requires-Dist: httpx>=0.28.1
Requires-Dist: inflection>=0.5.1
Requires-Dist: ipykernel>=7.1.0
Requires-Dist: jinja2-strcase>=0.0.2
Requires-Dist: jinja2>=3.1.6
Requires-Dist: websockets>=15.0.1
Provides-Extra: test
Requires-Dist: pytest-asyncio>=0.23.0; extra == 'test'
Requires-Dist: pytest-cov>=4.1.0; extra == 'test'
Requires-Dist: pytest>=8.0.0; extra == 'test'
